{
    "module": "wiki-viewer",
    "version": "v1.0.0",
    "status": "done",
    "category": "system",
    "description": "DEVKiTZ™ Wiki Viewer — Markdown Archiv mit Suche, TTS, Multi-Select, ZIP-Download, Mobile Version",
    "features": [
        { "id": "F-WKV-01", "name": "Markdown Renderer", "status": "done", "desc": "Vollständiger MD Parser: Tabellen, Code, Headings, Blockquotes, Listen, Checkboxen" },
        { "id": "F-WKV-02", "name": "Global Search + Highlight", "status": "done", "desc": "Volltextsuche über alle Seiten mit gelber Markierung" },
        { "id": "F-WKV-03", "name": "Sort & Filter", "status": "done", "desc": "Name (A-Z/Z-A), Dateigröße" },
        { "id": "F-WKV-04", "name": "TTS Vorlesen", "status": "done", "desc": "Web Speech API Deutsch, Stop/Start, Indikator" },
        { "id": "F-WKV-05", "name": "Multi-Select", "status": "done", "desc": "Checkboxen, Alle auswählen, Selektions-Leiste" },
        { "id": "F-WKV-06", "name": "ZIP Download", "status": "done", "desc": "JSZip: gewählte oder alle Seiten als .zip exportieren" },
        { "id": "F-WKV-07", "name": "Clipboard Copy", "status": "done", "desc": "Einzelne oder alle gewählten Seiten kopieren" },
        { "id": "F-WKV-08", "name": "Keyboard Navigation", "status": "done", "desc": "Arrow Keys Navigation, / für Suche, Esc = TTS Stop" },
        { "id": "F-WKV-09", "name": "Stats Panel", "status": "done", "desc": "Seiten, Wörter, KB, Auswahl-Counter" },
        { "id": "F-WKV-10", "name": "Mobile Version", "status": "done", "desc": "Vollständige Mobile-Optimierung als mobile.html" },
        { "id": "F-WKV-11", "name": "DkZ Design System v2", "status": "done", "desc": "Grid BG, 3 Blobs, Glassmorphism, Accent #fa1e4e" },
        { "id": "F-WKV-12", "name": "Shared Scripts", "status": "done", "desc": "dkz-debug.js + dkz-guide.js" }
    ],
    "dependencies": {
        "shared": ["dkz-debug.js", "dkz-guide.js"],
        "external": ["jszip@3.10.1", "Web Speech API"]
    },
    "wiki": {
        "path": "../../../../04_SYSTEM/DEVKITZ_WIKI/wiki/",
        "pages": 8
    }
}
